EVforecaster/EVforecasterUser.py
EVforecaster/__init__.py
EVforecasterModules/StatisticalTesting.py
EVforecasterModules/__init__.py
EVforecasterModules/charging_logic.py
EVforecasterModules/charging_logic_auxillary.py
EVforecasterModules/config.py
EVforecasterModules/data_loaders.py
EVforecasterModules/demand_curves.py
EVforecasterModules/pilots.py
evforecaster-1.0.0.dist-info/licenses/LICENSE
evforecaster-1.0.0.dist-info/METADATA
evforecaster-1.0.0.dist-info/WHEEL
evforecaster-1.0.0.dist-info/top_level.txt
evforecaster-1.0.0.dist-info/RECORD
