Metadata-Version: 2.4
Name: EVforecaster
Version: 1.0.0
Summary: A Python package for EVforc, an EV charging demand forecasting tool.
Author: Andriy Sinclair
License: MIT License
Requires-Python: >=3.10
License-File: LICENSE
Requires-Dist: matplotlib
Requires-Dist: numpy
Requires-Dist: ipykernel
Requires-Dist: pandas
Requires-Dist: scipy
Dynamic: license-file
